{
	"id": "e78516d4-6eec-4846-a1a8-480e6976d0be",
	"name": "New Environment",
	"values": [
		{
			"key": "",
			"value": "",
			"type": "default",
			"enabled": true
		},
		{
			"key": "authToken",
			"value": "",
			"type": "any",
			"enabled": true
		},
		{
			"key": "userEmail",
			"value": "",
			"type": "any",
			"enabled": true
		},
		{
			"key": "userName",
			"value": "",
			"type": "any",
			"enabled": true
		},
		{
			"key": "userMobile",
			"value": "",
			"type": "any",
			"enabled": true
		},
		{
			"key": "userId",
			"value": "",
			"type": "any",
			"enabled": true
		}
	],
	"_postman_variable_scope": "environment",
	"_postman_exported_at": "2025-09-17T10:07:07.870Z",
	"_postman_exported_using": "Postman/11.63.3"
}